practicals/__init__.py
practicals/practical1.py
practicals/practical10.py
practicals/practical11.py
practicals/practical12.py
practicals/practical13.py
practicals/practical2.py
practicals/practical3.py
practicals/practical4.py
practicals/practical5.py
practicals/practical6.py
practicals/practical7.py
practicals/practical8.py
practicals/practical9.py
prcodescht-0.1.0.dist-info/METADATA
prcodescht-0.1.0.dist-info/WHEEL
prcodescht-0.1.0.dist-info/top_level.txt
prcodescht-0.1.0.dist-info/RECORD
