Metadata-Version: 2.1
Name: prcodescht
Version: 0.1.0
Summary: A collection of practical codes
Author: Decrypt Cipher
Author-email: bagmarusaif@gmail.com
